Workbook

Sheet Resumo
A1: Cruzamento: Tally "5 ROTINAS PARA AUTOMATIZAR SUA OPERACAO" x base de conteudo
A2: Formulario xX8rVJ | dados lidos do Supabase xcihctupmfawtawbzwvm em 2026-08-26 15:22 | leitura apenas
A4: A ORIGEM
A5: Inscricoes no formulario | B5: =COUNTA(Inscritos!$F$2:$F$56) | C5: Uma linha por submissao unica de e-mail; duplicatas do mesmo e-mail foram agrupadas.
A6: Pessoas reais | B6: =COUNTIFS(Inscritos!$A$2:$A$56,"Real") | C6: Exclui 2 linhas de lixo (ASDF, Teste) e 2 inscricoes de teste interno.
A7: Com telefone | B7: =COUNTIFS(Inscritos!$A$2:$A$56,"Real",Inscritos!$I$2:$I$56,"+*") | C7: Este formulario coleta telefone - todas as inscricoes vieram com numero.
A8: Com e-mail corporativo | B8: =COUNTIFS(Inscritos!$A$2:$A$56,"Real",Inscritos!$G$2:$G$56,"sim") | C8: Dominio proprio: da a empresa mesmo sem perfil de LinkedIn.
A10: JA ERAM NOSSA AUDIENCIA
A11: Comentaram em post nosso | B11: =COUNTIFS(Inscritos!$A$2:$A$56,"Real",Inscritos!$B$2:$B$56,"Comentou em post") | C11: Cruzado por nome contra 3.249 comentarios coletados de 254 posts.
A12: dos quais confirmados | B12: =COUNTIFS(Inscritos!$A$2:$A$56,"Real",Inscritos!$L$2:$L$56,"MATCHED") | C12: Nome exato + especificidade ou dominio de e-mail batendo com a empresa.
A13: dos quais a revisar | B13: =COUNTIFS(Inscritos!$A$2:$A$56,"Real",Inscritos!$L$2:$L$56,"REVIEW") | C13: Nome bate mas falta evidencia independente. Nao afirmar sem conferir.
A14: Baixaram outro lead magnet | B14: =COUNTIFS(Inscritos!$A$2:$A$56,"Real",Inscritos!$B$2:$B$56,"Baixou outro lead magnet") | C14: E-mail ja estava na base do Tally, mas nunca comentou.
A15: Audiencia nova | B15: =COUNTIFS(Inscritos!$A$2:$A$56,"Real",Inscritos!$B$2:$B$56,"Novo") | C15: Nem comentario, nem download anterior.
A17: O QUE ESSE GRUPO PARECE
A18: Media de funcionarios (casados) | B18: =IFERROR(AVERAGEIFS(Inscritos!$W$2:$W$56,Inscritos!$A$2:$A$56,"Real",Inscritos!$W$2:$W$56,">0"),"-") | C18: Puxada pelas tres contas grandes; a mediana esta muito abaixo.
A19: Qualified pelo score atual | B19: =COUNTIFS(Inscritos!$A$2:$A$56,"Real",Inscritos!$AB$2:$AB$56,"qualified") | C19: Score que o pipeline de prospeccao usa hoje.
A20: Disqualified pelo score atual | B20: =COUNTIFS(Inscritos!$A$2:$A$56,"Real",Inscritos!$AB$2:$AB$56,"disqualified") | C20: Inclui quase todos os mais engajados - ver aba ICP.
A21: Ja prospectados | B21: =COUNTIFS(Inscritos!$A$2:$A$56,"Real",Inscritos!$AN$2:$AN$56,"<>não") | C21: Cruzado com lead_outreach (136 registros).
A22: Agendaram reuniao | B22: =COUNTIFS(Inscritos!$A$2:$A$56,"Real",Inscritos!$AQ$2:$AQ$56,"<>não") | C22: Cruzado com lead_magnet_bookings.
A24: POR QUE O POST DE 25/08 NAO APARECE NA BASE
A25: O credito da Apify acabou. O coletor de LinkedIn roda 09:30 UTC; em 25/08 rodou e funcionou, mas o post so subiu ~12:00 - passou depois da coleta. A rodada de 26/08, que pegaria o post, falhou: "you will exceed your remaining usage of $0.001342". Detalhe completo na aba Diagnostico.

Sheet Inscritos
A1: Classificacao | B1: Ja era audiencia? | C1: Nome (Tally) | D1: Primeiro nome | E1: Sobrenome | F1: E-mail | G1: Corporativo | H1: Dominio | I1: Telefone | J1: Inscrito em | K1: Inscricoes neste form | L1: Match | M1: Metodo do match | N1: Confianca | O1: Evidencia | P1: Leads candidatos | Q1: LinkedIn | R1: Nome no LinkedIn | S1: Cargo / headline | T1: Senioridade | U1: Area | V1: Empresa | W1: Funcionarios | X1: Industria | Y1: Cidade | Z1: Estado | AA1: Pais | AB1: ICP hoje | AC1: Score ICP | AD1: Motivo do ICP | AE1: Comentarios | AF1: 1o comentario | AG1: Ultimo comentario | AH1: Posts comentados | AI1: CTAs que respondeu | AJ1: Outros lead magnets | AK1: Quais lead magnets | AL1: Primeiro contato | AM1: Dias na base | AN1: Prospectado | AO1: Canal | AP1: Data do outreach | AQ1: Agendou reuniao | AR1: Telefone ja registrado
A2: Real | B2: Comentou em post | C2: André Soczek | D2: André | E2: Soczek | F2: andre@apartamentoscuritiba.com.br | G2: sim | H2: apartamentoscuritiba.com.br | I2: +5541995281092 | J2: 2026-08-25 12:52 | K2: 1 | L2: MATCHED | M2: nome_exato+dominio_empresa | N2: 0.94 | O2: dominio_empresa + apos_comentario | P2: 1 | Q2: https://www.linkedin.com/in/andre-soczek | R2: André Soczek | S2: Fundador | T2: c-level | U2: outro | V2: Apartamentos Curitiba | W2: 8 | X2: Real Estate | AB2: disqualified | AC2: 30 | AD2: A empresa tem apenas 8 colaboradores, o que não atende ao critério de porte mínimo. | AE2: 1 | AF2: 2026-08-13 | AG2: 2026-08-13 | AH2: 2026-08-11 s/CTA | AJ2: 0 | AL2: 2026-08-25 | AM2: 0 | AN2: não | AQ2: não
A3: Real | B3: Comentou em post | C3: Luan Garcia Hinkel | D3: Luan | E3: Garcia Hinkel | F3: luan.hinkel@newfold.com | G3: sim | H3: newfold.com | I3: +5548991996450 | J3: 2026-08-25 13:03 | K3: 1 | L3: MATCHED | M3: nome_exato_especifico | N3: 0.85 | O3: apos_comentario | P3: 1 | Q3: https://www.linkedin.com/in/luanhinkel | R3: Luan Garcia Hinkel | S3: Sales Operations Junior | T3: operacional | U3: outro | V3: HostGator América Latina | W3: 316 | X3: Technology, Information and Internet | AB3: disqualified | AC3: 30 | AD3: O lead ocupa um cargo júnior e não se encaixa nos critérios de qualificação para a consultoria. | AE3: 2 | AF3: 2026-07-29 | AG3: 2026-08-12 | AH3: 2026-07-29 OS | 2026-08-11 s/CTA | AI3: OS | AJ3: 0 | AL3: 2026-08-25 | AM3: 0 | AN3: não | AQ3: não
A4: Real | B4: Comentou em post | C4: João Pedro Maya | D4: João Pedro | E4: Maya | F4: joao.pedro.maya@gmail.com | G4: não | H4: gmail.com | I4: +5521998522611 | J4: 2026-08-25 17:55 | K4: 1 | L4: MATCHED | M4: nome_exato_especifico | N4: 0.85 | O4: apos_comentario | P4: 1 | Q4: https://www.linkedin.com/in/joao-pedro-maya | R4: João Pedro Maya | S4: Projetos | Reestruturação de processos | Operações | Trilingue | T4: desconhecido | U4: desconhecido | AB4: disqualified | AC4: 0 | AD4: O lead está sem emprego atual, portanto não pode ser qualificado. | AE4: 1 | AF4: 2026-08-12 | AG4: 2026-08-12 | AH4: 2026-08-11 s/CTA | AJ4: 0 | AL4: 2026-08-25 | AM4: 0 | AN4: não | AQ4: não
A5: Real | B5: Comentou em post | C5: marina lemos | D5: marina | E5: lemos | F5: marinarlemos08@gmail.com | G5: não | H5: gmail.com | I5: +5548988191425 | J5: 2026-08-25 18:32 | K5: 1 | L5: REVIEW | M5: nome_parcial | N5: 0.45 | O5: apos_comentario | P5: 1 | Q5: https://www.linkedin.com/in/marinarlemos | R5: Marina Rachewsky Lemos | S5: Embaixadora | Influenciadora | T5: gerencia | U5: vendas | V5: HubSpot | W5: 12235 | X5: Software Development | AB5: qualified | AC5: 95 | AD5: A lead possui vasta experiência em liderança e implementação de times e processos comerciais em grandes empresas B2B, e a empresa atual (HubSpot) é de grande porte, com o tema do post indicando uma dor clara em forecast de vendas. | AE5: 2 | AF5: 2026-05-28 | AG5: 2026-07-29 | AH5: 2026-05-27 Sem CTA | 2026-07-29 OS | AI5: OS | AJ5: 1 | AK5: Acesse o grupo VIP da Comunidade Playbook Lab | AL5: 2026-08-25 | AM5: 0 | AN5: ignored | AO5: linkedin | AP5: 2026-07-05 | AQ5: não | AR5: REVIEW
A6: Real | B6: Comentou em post | C6: Rodrigo Nascimento | D6: Rodrigo | E6: Nascimento | F6: rodrigo.nsc@gmail.com | G6: não | H6: gmail.com | I6: +5548988250523 | J6: 2026-08-25 12:49 | K6: 1 | L6: REVIEW | M6: nome_exato_generico | N6: 0.6 | O6: apos_comentario | P6: 1 | Q6: https://www.linkedin.com/in/rodrigonsc | R6: Rodrigo Nascimento | S6: Head Comercial | Head de Produto · SaaS · RevOps · Go-to-Market · Pré-vendas · IA aplicada a Vendas | T6: desconhecido | U6: desconhecido | V6: Keeta | W6: 6638 | X6: Software Development | AB6: qualified | AC6: 55 | AD6: Migrado da revisão (17/08): decisor comercial em empresa 200+ rejeitado por glitch (empresa atual não veio no scrape) — VERIFICAR vínculo atual. Motivo original: O lead está sem emprego atual, portanto não pode ser qualificado. | AE6: 2 | AF6: 2026-07-29 | AG6: 2026-08-12 | AH6: 2026-07-29 OS | 2026-08-11 s/CTA | AI6: OS | AJ6: 0 | AL6: 2026-08-25 | AM6: 0 | AN6: não | AQ6: não | AR6: REVIEW
A7: Real | B7: Comentou em post | C7: Celio Andrade | D7: Celio | E7: Andrade | F7: cmilodeandrade@gmail.com | G7: não | H7: gmail.com | I7: +5547996342583 | J7: 2026-08-25 12:57 | K7: 1 | L7: REVIEW | M7: nome_parcial | N7: 0.45 | O7: apos_comentario | P7: 1 | Q7: https://www.linkedin.com/in/celio-milo-de-andrade-96644973 | R7: Celio Milo de Andrade | S7: Coordenador de licitações | T7: coordenacao | U7: outro | V7: Cantu Inc | W7: 1658 | X7: Retail | AB7: disqualified | AC7: 45 | AD7: O lead ocupa um cargo de coordenação em uma área que não se alinha com as áreas de interesse da Playbook Lab e não está em um setor de vendas ou tecnologia. | AE7: 1 | AF7: 2026-07-30 | AG7: 2026-07-30 | AH7: 2026-07-29 OS | AI7: OS | AJ7: 2 | AK7: Claude para Pequenos Negócios | O Setup inicial do OS da sua empresa | AL7: 2026-07-24 | AM7: 32 | AN7: não | AQ7: não
A8: Real | B8: Comentou em post | C8: Vinícius Silva | D8: Vinícius | E8: Silva | F8: viniciuscmx01@gmail.com | G8: não | H8: gmail.com | I8: +5521998939333 | J8: 2026-08-25 17:24 | K8: 1 | L8: REVIEW | M8: nome_exato_generico | N8: 0.6 | O8: apos_comentario | P8: 1 | Q8: https://www.linkedin.com/in/theviniciusssilva | R8: Vinícius Silva | S8: Consultor & Estrategista Digital | T8: desconhecido | U8: outro | V8: Aigle Aeternus Hub | AB8: disqualified | AC8: 45 | AD8: O lead é um consultor digital, mas não ocupa um cargo alto em uma empresa com mais de 200 colaboradores. | AE8: 4 | AF8: 2026-07-03 | AG8: 2026-08-11 | AH8: 2026-07-03 FABLE | 2026-07-14 FLOW | 2026-07-29 OS | 2026-08-11 s/CTA | AI8: FABLE, FLOW, OS | AJ8: 0 | AL8: 2026-08-25 | AM8: 0 | AN8: não | AQ8: não
A9: Real | B9: Comentou em post | C9: Eduardo Abreu | D9: Eduardo | E9: Abreu | F9: eduardo.abreu02@gmail.com | G9: não | H9: gmail.com | I9: +5511939402808 | J9: 2026-08-25 13:38 | K9: 1 | L9: REVIEW | M9: nome_exato_generico | N9: 0.6 | O9: apos_comentario | P9: 1 | Q9: https://www.linkedin.com/in/eduardo-abreu-comercial | R9: Eduardo Abreu | S9: Executivo de contas | T9: desconhecido | U9: vendas | V9: Business Innovation Ltda | AB9: disqualified | AC9: 40 | AD9: O cargo de Executivo de Contas não é considerado uma posição de liderança com poder de decisão de compra. | AE9: 1 | AF9: 2026-08-12 | AG9: 2026-08-12 | AH9: 2026-08-11 s/CTA | AJ9: 0 | AL9: 2026-08-25 | AM9: 0 | AN9: não | AQ9: não
A10: Real | B10: Comentou em post | C10: Cíntia Fonseca | D10: Cíntia | E10: Fonseca | F10: cintiafonseeca@gmail.com | G10: não | H10: gmail.com | I10: +5513996215600 | J10: 2026-08-25 12:52 | K10: 1 | L10: REVIEW | M10: nome_exato_generico | N10: 0.6 | O10: apos_comentario | P10: 1 | Q10: https://www.linkedin.com/in/c%C3%ADntia-fonseca-638a251aa | R10: Cíntia Fonseca | S10: SDR / BDR | T10: operacional | U10: vendas | V10: Vkron Agência de Marketing Digital | W10: 27 | X10: Marketing Services | AB10: disqualified | AC10: 30 | AD10: O cargo de SDR/BDR não é considerado um cargo alto e a empresa tem menos de 200 colaboradores. | AE10: 1 | AF10: 2026-08-12 | AG10: 2026-08-12 | AH10: 2026-08-11 s/CTA | AJ10: 1 | AK10: 36 Skills de SDR para Claude | AL10: 2026-08-25 | AM10: 0 | AN10: não | AQ10: não
A11: Real | B11: Comentou em post | C11: Gabriel Lima | D11: Gabriel | E11: Lima | F11: ga.lima@reply.com | G11: sim | H11: reply.com | I11: +5511970452004 | J11: 2026-08-25 12:50 | K11: 1 | L11: REVIEW | M11: nome_exato_generico | N11: 0.6 | O11: apos_comentario | P11: 1 | Q11: https://www.linkedin.com/in/gabriel-de-lima-p | R11: Gabriel de Lima P. | S11: Executivo de Vendas | Inside Sales | SDR | BDR | Hunter | B2B | Outbound | Analista TI | Analista de Suporte | Cloud | Projetos Infraestrutura | ADS | Programador | Tecnologia | SQL | T11: desconhecido | U11: vendas | V11: Senior Mega SPO | W11: 11 | AB11: disqualified | AC11: 30 | AD11: O lead é um SDR, que não é um cargo de decisão e a empresa tem apenas 11 colaboradores. | AE11: 1 | AF11: 2026-08-11 | AG11: 2026-08-11 | AH11: 2026-08-11 s/CTA | AJ11: 0 | AL11: 2026-08-25 | AM11: 0 | AN11: não | AQ11: não
A12: Real | B12: Comentou em post | C12: Hudson Oliveira | D12: Hudson | E12: Oliveira | F12: hudson.dias91@gmail.com | G12: não | H12: gmail.com | I12: +5519991508069 | J12: 2026-08-26 11:36 | K12: 1 | L12: REVIEW | M12: nome_parcial | N12: 0.45 | O12: apos_comentario | P12: 1 | Q12: https://www.linkedin.com/in/hudson-leonardo-oliveira-718a4944 | R12: Hudson Leonardo Oliveira | S12: Sócio e Consultor de Negócios | T12: diretoria | U12: outro | V12: Consultólogo | W12: 2 | X12: Business Consulting and Services | AB12: disqualified | AC12: 30 | AD12: A empresa atual tem apenas 2 colaboradores, o que não atende ao critério de porte mínimo. | AE12: 2 | AF12: 2026-07-30 | AG12: 2026-08-11 | AH12: 2026-07-29 OS | 2026-08-11 s/CTA | AI12: OS | AJ12: 0 | AL12: 2026-08-26 | AM12: 0 | AN12: não | AQ12: não
A13: Real | B13: Comentou em post | C13: patricia zaniratto | D13: patricia | E13: zaniratto | F13: zanirattocomercial@gmail.com | G13: não | H13: gmail.com | I13: +5511991625614 | J13: 2026-08-25 13:06 | K13: 1 | L13: REVIEW | M13: nome_exato_generico | N13: 0.6 | O13: apos_comentario | P13: 1 | Q13: https://www.linkedin.com/in/patricia-zaniratto-a4438948 | R13: Patricia Zaniratto | S13: Especialista em Prospecção B2B | T13: operacional | U13: vendas | V13: Zaniratto Comercial | AB13: disqualified | AC13: 30 | AD13: O cargo de especialista em prospecção B2B não é considerado um cargo alto com poder de decisão. | AE13: 1 | AF13: 2026-08-12 | AG13: 2026-08-12 | AH13: 2026-08-11 s/CTA | AJ13: 0 | AL13: 2026-08-25 | AM13: 0 | AN13: não | AQ13: não
A14: Real | B14: Comentou em post | C14: Rafael Silva | D14: Rafael | E14: Silva | F14: orafaelnsilva@gmail.com | G14: não | H14: gmail.com | I14: +5511972233392 | J14: 2026-08-25 14:04 | K14: 1 | L14: REVIEW | M14: nome_parcial | N14: 0.45 | O14: apos_comentario | P14: 3 | Q14: https://www.linkedin.com/in/orafaelnunes | R14: Rafael Nunes da Silva | S14: Estratégia Digital, Inovação e Produtos SaaS | Foco em Crescimento, Dados e Experiência do Usuário | T14: desconhecido | U14: desconhecido | AB14: disqualified | AC14: 30 | AD14: O lead está sem emprego atual, o que impede a qualificação. | AE14: 2 | AF14: 2026-07-14 | AG14: 2026-08-11 | AH14: 2026-07-14 FLOW | 2026-08-11 s/CTA | AI14: FLOW | AJ14: 3 | AK14: 36 Skills de SDR para Claude | AL14: 2026-08-11 | AM14: 14 | AN14: não | AQ14: não
A15: Real | B15: Comentou em post | C15: Sidnei Brianti | D15: Sidnei | E15: Brianti | F15: scbrianti2022@gmail.com | G15: não | H15: gmail.com | I15: +5519982450707 | J15: 2026-08-25 14:27 | K15: 1 | L15: REVIEW | M15: nome_exato_generico | N15: 0.6 | O15: apos_comentario | P15: 1 | Q15: https://www.linkedin.com/in/sidnei-brianti | R15: Sidnei Brianti | S15: Fundador | T15: c-level | U15: outro | V15: LinkaTudo | W15: 2 | AB15: disqualified | AC15: 30 | AD15: Embora seja fundador, a empresa tem apenas 2 colaboradores, o que não atende ao critério de porte mínimo. | AE15: 1 | AF15: 2026-08-11 | AG15: 2026-08-11 | AH15: 2026-08-11 s/CTA | AJ15: 3 | AK15: 36 Skills de SDR para Claude | AL15: 2026-08-11 | AM15: 14 | AN15: não | AQ15: não
A16: Real | B16: Comentou em post | C16: Nicolò de Marle | D16: Nicolò | E16: de Marle | F16: nicodemarle@gmail.com | G16: não | H16: gmail.com | I16: +5541991090330 | J16: 2026-08-25 13:13 | K16: 1 | L16: REVIEW | M16: nome_parcial | N16: 0.45 | O16: apos_comentario | P16: 1 | Q16: https://www.linkedin.com/in/nicogiustidemarle | R16: Nicolò Giusti de Marle | S16: Co-Founder | T16: c-level | U16: outro | V16: LUXIA | W16: 3 | X16: Software Development | Y16: Curitiba | Z16: Paraná | AA16: Brazil | AB16: disqualified | AC16: 0 | AD16: A empresa LUXIA possui apenas 3 colaboradores, não atendendo ao critério de porte mínimo. | AE16: 1 | AF16: 2026-08-21 | AG16: 2026-08-21 | AH16: 2026-08-11 s/CTA | AJ16: 0 | AL16: 2026-08-25 | AM16: 0 | AN16: não | AQ16: não
A17: Real | B17: Baixou outro lead magnet | C17: Andrei Lucas | D17: Andrei | E17: Lucas | F17: andreidias.96@outlook.com | G17: não | H17: outlook.com | I17: +5511981735119 | J17: 2026-08-25 13:31 | K17: 1 | L17: NOT_FOUND | P17: 0 | AE17: 0 | AJ17: 1 | AK17: O Setup inicial do OS da sua empresa | AL17: 2026-07-30 | AM17: 26 | AN17: não | AQ17: não
A18: Real | B18: Baixou outro lead magnet | C18: Gustavo Santos | D18: Gustavo | E18: Santos | F18: gustavomaedoyt@gmail.com | G18: não | H18: gmail.com | I18: +5511997159940 | J18: 2026-08-25 13:07 | K18: 1 | L18: NOT_FOUND | P18: 0 | AE18: 0 | AJ18: 1 | AK18: O Setup inicial do OS da sua empresa | AL18: 2026-08-09 | AM18: 16 | AN18: não | AQ18: não
A19: Real | B19: Baixou outro lead magnet | C19: Rafael Comin | D19: Rafael | E19: Comin | F19: clientes.rafaelcomin@gmail.com | G19: não | H19: gmail.com | I19: +5554999166672 | J19: 2026-08-25 13:00 | K19: 1 | L19: NOT_FOUND | P19: 0 | AE19: 0 | AJ19: 1 | AK19: Claude Cowork para Vendas | AL19: 2026-08-11 | AM19: 14 | AN19: não | AQ19: não
A20: Real | B20: Novo | C20: Andre Sousa | D20: Andre | E20: Sousa | F20: andre.sousa@nilg.ai | G20: sim | H20: nilg.ai | I20: +351938016732 | J20: 2026-08-26 07:48 | K20: 1 | L20: NOT_FOUND | P20: 0 | AE20: 0 | AJ20: 0 | AL20: 2026-08-26 | AM20: 0 | AN20: não | AQ20: não
A21: Real | B21: Novo | C21: Antonio Hiaygni Guimarães | D21: Antonio Hiaygni | E21: Guimarães | F21: hiaygnifg@gmail.com | G21: não | H21: gmail.com | I21: +5586998065981 | J21: 2026-08-25 12:59 | K21: 1 | L21: NOT_FOUND | P21: 0 | AE21: 0 | AJ21: 0 | AL21: 2026-08-25 | AM21: 0 | AN21: não | AQ21: não
A22: Real | B22: Novo | C22: Arielle Domanski | D22: Arielle | E22: Domanski | F22: arielle.domanski@madeiramadeira.com.br | G22: sim | H22: madeiramadeira.com.br | I22: +5541996682298 | J22: 2026-08-25 19:05 | K22: 1 | L22: NOT_FOUND | P22: 0 | AE22: 0 | AJ22: 0 | AL22: 2026-08-25 | AM22: 0 | AN22: não | AQ22: não
A23: Real | B23: Novo | C23: Bruno Zambon | D23: Bruno | E23: Zambon | F23: bpz.adm@gmail.com | G23: não | H23: gmail.com | I23: +5527981319002 | J23: 2026-08-25 13:11 | K23: 1 | L23: NOT_FOUND | P23: 0 | AE23: 0 | AJ23: 0 | AL23: 2026-08-25 | AM23: 0 | AN23: não | AQ23: não
A24: Real | B24: Novo | C24: Carina Francioni | D24: Carina | E24: Francioni | F24: carinafrancionic@gmail.com | G24: não | H24: gmail.com | I24: +5547988528975 | J24: 2026-08-25 12:53 | K24: 1 | L24: NOT_FOUND | P24: 0 | AE24: 0 | AJ24: 0 | AL24: 2026-08-25 | AM24: 0 | AN24: não | AQ24: não
A25: Real | B25: Novo | C25: Carolina Pereira | D25: Carolina | E25: Pereira | F25: carolina.botelho@braziljournal.com | G25: sim | H25: braziljournal.com | I25: +5511991375461 | J25: 2026-08-26 14:15 | K25: 1 | L25: NOT_FOUND | P25: 0 | AE25: 0 | AJ25: 0 | AL25: 2026-08-26 | AM25: 0 | AN25: não | AQ25: não
A26: Real | B26: Novo | C26: Daiane Carvalho | D26: Daiane | E26: Carvalho | F26: daiane.sacc@gmail.com | G26: não | H26: gmail.com | I26: +5511969116674 | J26: 2026-08-25 23:52 | K26: 1 | L26: NOT_FOUND | P26: 0 | AE26: 0 | AJ26: 0 | AL26: 2026-08-25 | AM26: 0 | AN26: não | AQ26: não
A27: Real | B27: Novo | C27: diogo moraes | D27: diogo | E27: moraes | F27: diogomoraes08@icloud.com | G27: não | H27: icloud.com | I27: +5516992584779 | J27: 2026-08-25 13:00 | K27: 1 | L27: NOT_FOUND | P27: 0 | AE27: 0 | AJ27: 0 | AL27: 2026-08-25 | AM27: 0 | AN27: não | AQ27: não
A28: Real | B28: Novo | C28: Débora Cristine Barboza da Matta | D28: Débora Cristine | E28: Barboza da Matta | F28: debsbarboza19@gmail.com | G28: não | H28: gmail.com | I28: +5581999737424 | J28: 2026-08-25 13:47 | K28: 1 | L28: NOT_FOUND | P28: 0 | AE28: 0 | AJ28: 0 | AL28: 2026-08-25 | AM28: 0 | AN28: não | AQ28: não
A29: Real | B29: Novo | C29: Eduardo Moura | D29: Eduardo | E29: Moura | F29: eduardo@savessaude.com.br | G29: sim | H29: savessaude.com.br | I29: +5511978253731 | J29: 2026-08-25 14:03 | K29: 1 | L29: NOT_FOUND | P29: 0 | AE29: 0 | AJ29: 0 | AL29: 2026-08-25 | AM29: 0 | AN29: não | AQ29: não
A30: Real | B30: Novo | C30: Fabiana Bittencourt | D30: Fabiana | E30: Bittencourt | F30: bittencourt.sfabiana@gmail.com | G30: não | H30: gmail.com | I30: +5511970393535 | J30: 2026-08-25 22:01 | K30: 1 | L30: NOT_FOUND | P30: 0 | AE30: 0 | AJ30: 0 | AL30: 2026-08-25 | AM30: 0 | AN30: não | AQ30: não
A31: Real | B31: Novo | C31: Flavia de Almeida | D31: Flavia | E31: de Almeida | F31: comercialflavianunes@gmail.com | G31: não | H31: gmail.com | I31: +5521988982808 | J31: 2026-08-25 16:53 | K31: 1 | L31: NOT_FOUND | P31: 0 | AE31: 0 | AJ31: 0 | AL31: 2026-08-25 | AM31: 0 | AN31: não | AQ31: não
... A52: Real | B52: Novo | C52: Vinicius Assini | D52: Vinicius | E52: Assini | F52: vinicius.assini@gmail.com | G52: não | H52: gmail.com | I52: +5547999990000 | J52: 2026-08-25 13:47 | K52: 1 | L52: NOT_FOUND | P52: 0 | AE52: 0 | AJ52: 0 | AL52: 2026-08-25 | AM52: 0 | AN52: não | AQ52: não
A53: Teste interno | B53: Baixou outro lead magnet | C53: FELIPE NUNES | D53: FELIPE | E53: NUNES | F53: fereservas@gmail.com | G53: não | H53: gmail.com | I53: +551952960701 | J53: 2026-08-17 20:38 | K53: 1 | L53: NOT_FOUND | P53: 0 | AE53: 0 | AJ53: 10 | AK53: Claude Flabe 5 | KipFlow - API brasileira boa de verdade | O Setup inicial do OS da sua empresa | 36 Skills de SDR para Claude | AL53: 2026-07-03 | AM53: 45 | AN53: não | AQ53: não
A54: Teste interno | B54: Baixou outro lead magnet | C54: FELIPE NUNES | D54: FELIPE | E54: NUNES | F54: felipearian10197@gmail.com | G54: não | H54: gmail.com | I54: +5511952960701 | J54: 2026-08-25 12:04 | K54: 1 | L54: NOT_FOUND | P54: 0 | AE54: 0 | AJ54: 3 | AK54: Claude Flabe 5 | KipFlow - API brasileira boa de verdade | 36 Skills de SDR para Claude | AL54: 2026-07-03 | AM54: 53 | AN54: não | AQ54: não
A55: Lixo | B55: Baixou outro lead magnet | C55: Teste Teste | D55: Teste | E55: Teste | F55: teste@teste.com.br | G55: sim | H55: teste.com.br | I55: +5531999999999 | J55: 2026-08-25 13:25 | K55: 1 | L55: NOT_FOUND | P55: 0 | AE55: 0 | AJ55: 3 | AK55: KipFlow - API brasileira boa de verdade | 18 MCPs + o guia de instalação completo | 36 Skills de SDR para Claude | AL55: 2026-07-14 | AM55: 42 | AN55: não | AQ55: não
A56: Lixo | B56: Novo | C56: ASDF ASDF | D56: ASDF | E56: ASDF | F56: asdf@sdsa.com | G56: sim | H56: sdsa.com | I56: +5541999999999 | J56: 2026-08-25 12:59 | K56: 1 | L56: NOT_FOUND | P56: 0 | AE56: 0 | AJ56: 0 | AL56: 2026-08-25 | AM56: 0 | AN56: não | AQ56: não

Sheet Matches
A1: Status | B1: Metodo | C1: Confianca | D1: Evidencia | E1: Candidato | F1: de | G1: Tipo de nome | H1: Nome (Tally) | I1: E-mail | J1: Telefone | K1: Inscrito em | L1: Nome no LinkedIn | M1: LinkedIn | N1: Cargo | O1: Empresa | P1: Funcionarios | Q1: ICP | R1: Score | S1: Comentarios | T1: Posts comentados
A2: MATCHED | B2: nome_exato+dominio_empresa | C2: 0.94 | D2: dominio_empresa + apos_comentario | E2: 1 | F2: 1 | G2: exato | H2: André Soczek | I2: andre@apartamentoscuritiba.com.br | J2: +5541995281092 | K2: 2026-08-25 12:52 | L2: André Soczek | M2: https://www.linkedin.com/in/andre-soczek | N2: Fundador | O2: Apartamentos Curitiba | P2: 8 | Q2: disqualified | R2: 30 | S2: 1 | T2: 2026-08-11 s/CTA
A3: MATCHED | B3: nome_exato_especifico | C3: 0.85 | D3: apos_comentario | E3: 1 | F3: 1 | G3: exato | H3: João Pedro Maya | I3: joao.pedro.maya@gmail.com | J3: +5521998522611 | K3: 2026-08-25 17:55 | L3: João Pedro Maya | M3: https://www.linkedin.com/in/joao-pedro-maya | N3: Projetos | Reestruturação de processos | Operações | Trilingue | Q3: disqualified | R3: 0 | S3: 1 | T3: 2026-08-11 s/CTA
A4: MATCHED | B4: nome_exato_especifico | C4: 0.85 | D4: apos_comentario | E4: 1 | F4: 1 | G4: exato | H4: Luan Garcia Hinkel | I4: luan.hinkel@newfold.com | J4: +5548991996450 | K4: 2026-08-25 13:03 | L4: Luan Garcia Hinkel | M4: https://www.linkedin.com/in/luanhinkel | N4: Sales Operations Junior | O4: HostGator América Latina | P4: 316 | Q4: disqualified | R4: 30 | S4: 2 | T4: 2026-07-29 OS | 2026-08-11 s/CTA
A5: REVIEW | B5: nome_exato_generico | C5: 0.6 | D5: apos_comentario | E5: 1 | F5: 1 | G5: exato | H5: Cíntia Fonseca | I5: cintiafonseeca@gmail.com | J5: +5513996215600 | K5: 2026-08-25 12:52 | L5: Cíntia Fonseca | M5: https://www.linkedin.com/in/c%C3%ADntia-fonseca-638a251aa | N5: SDR / BDR | O5: Vkron Agência de Marketing Digital | P5: 27 | Q5: disqualified | R5: 30 | S5: 1 | T5: 2026-08-11 s/CTA
A6: REVIEW | B6: nome_exato_generico | C6: 0.6 | D6: apos_comentario | E6: 1 | F6: 1 | G6: exato | H6: Eduardo Abreu | I6: eduardo.abreu02@gmail.com | J6: +5511939402808 | K6: 2026-08-25 13:38 | L6: Eduardo Abreu | M6: https://www.linkedin.com/in/eduardo-abreu-comercial | N6: Executivo de contas | O6: Business Innovation Ltda | Q6: disqualified | R6: 40 | S6: 1 | T6: 2026-08-11 s/CTA
A7: REVIEW | B7: nome_exato_generico | C7: 0.6 | D7: apos_comentario | E7: 1 | F7: 1 | G7: exato | H7: Gabriel Lima | I7: ga.lima@reply.com | J7: +5511970452004 | K7: 2026-08-25 12:50 | L7: Gabriel de Lima P. | M7: https://www.linkedin.com/in/gabriel-de-lima-p | N7: Executivo de Vendas | Inside Sales | SDR | BDR | Hunter | B2B | Outbound | Analista TI | Analista de Suporte | Cloud | Projetos Infraestrutura | ADS | Programador | Tecnologia | SQL | O7: Senior Mega SPO | P7: 11 | Q7: disqualified | R7: 30 | S7: 1 | T7: 2026-08-11 s/CTA
A8: REVIEW | B8: nome_exato_generico | C8: 0.6 | D8: apos_comentario | E8: 1 | F8: 1 | G8: exato | H8: Rodrigo Nascimento | I8: rodrigo.nsc@gmail.com | J8: +5548988250523 | K8: 2026-08-25 12:49 | L8: Rodrigo Nascimento | M8: https://www.linkedin.com/in/rodrigonsc | N8: Head Comercial | Head de Produto · SaaS · RevOps · Go-to-Market · Pré-vendas · IA aplicada a Vendas | O8: Keeta | P8: 6638 | Q8: qualified | R8: 55 | S8: 2 | T8: 2026-07-29 OS | 2026-08-11 s/CTA
A9: REVIEW | B9: nome_exato_generico | C9: 0.6 | D9: apos_comentario | E9: 1 | F9: 1 | G9: exato | H9: Sidnei Brianti | I9: scbrianti2022@gmail.com | J9: +5519982450707 | K9: 2026-08-25 14:27 | L9: Sidnei Brianti | M9: https://www.linkedin.com/in/sidnei-brianti | N9: Fundador | O9: LinkaTudo | P9: 2 | Q9: disqualified | R9: 30 | S9: 1 | T9: 2026-08-11 s/CTA
A10: REVIEW | B10: nome_exato_generico | C10: 0.6 | D10: apos_comentario | E10: 1 | F10: 1 | G10: exato | H10: Vinícius Silva | I10: viniciuscmx01@gmail.com | J10: +5521998939333 | K10: 2026-08-25 17:24 | L10: Vinícius Silva | M10: https://www.linkedin.com/in/theviniciusssilva | N10: Consultor & Estrategista Digital | O10: Aigle Aeternus Hub | Q10: disqualified | R10: 45 | S10: 4 | T10: 2026-07-03 FABLE | 2026-07-14 FLOW | 2026-07-29 OS | 2026-08-11 s/CTA
A11: REVIEW | B11: nome_exato_generico | C11: 0.6 | D11: apos_comentario | E11: 1 | F11: 1 | G11: exato | H11: patricia zaniratto | I11: zanirattocomercial@gmail.com | J11: +5511991625614 | K11: 2026-08-25 13:06 | L11: Patricia Zaniratto | M11: https://www.linkedin.com/in/patricia-zaniratto-a4438948 | N11: Especialista em Prospecção B2B | O11: Zaniratto Comercial | Q11: disqualified | R11: 30 | S11: 1 | T11: 2026-08-11 s/CTA
A12: REVIEW | B12: nome_parcial | C12: 0.45 | D12: apos_comentario | E12: 1 | F12: 1 | G12: primeiro_ultimo | H12: Celio Andrade | I12: cmilodeandrade@gmail.com | J12: +5547996342583 | K12: 2026-08-25 12:57 | L12: Celio Milo de Andrade | M12: https://www.linkedin.com/in/celio-milo-de-andrade-96644973 | N12: Coordenador de licitações | O12: Cantu Inc | P12: 1658 | Q12: disqualified | R12: 45 | S12: 1 | T12: 2026-07-29 OS
A13: REVIEW | B13: nome_parcial | C13: 0.45 | D13: apos_comentario | E13: 1 | F13: 1 | G13: primeiro_ultimo | H13: Hudson Oliveira | I13: hudson.dias91@gmail.com | J13: +5519991508069 | K13: 2026-08-26 11:36 | L13: Hudson Leonardo Oliveira | M13: https://www.linkedin.com/in/hudson-leonardo-oliveira-718a4944 | N13: Sócio e Consultor de Negócios | O13: Consultólogo | P13: 2 | Q13: disqualified | R13: 30 | S13: 2 | T13: 2026-07-29 OS | 2026-08-11 s/CTA
A14: REVIEW | B14: nome_parcial | C14: 0.45 | D14: apos_comentario | E14: 1 | F14: 1 | G14: primeiro_ultimo | H14: marina lemos | I14: marinarlemos08@gmail.com | J14: +5548988191425 | K14: 2026-08-25 18:32 | L14: Marina Rachewsky Lemos | M14: https://www.linkedin.com/in/marinarlemos | N14: Embaixadora | Influenciadora | O14: HubSpot | P14: 12235 | Q14: qualified | R14: 95 | S14: 2 | T14: 2026-05-27 Sem CTA | 2026-07-29 OS
A15: REVIEW | B15: nome_parcial | C15: 0.45 | D15: apos_comentario | E15: 1 | F15: 1 | G15: primeiro_ultimo | H15: Nicolò de Marle | I15: nicodemarle@gmail.com | J15: +5541991090330 | K15: 2026-08-25 13:13 | L15: Nicolò Giusti de Marle | M15: https://www.linkedin.com/in/nicogiustidemarle | N15: Co-Founder | O15: LUXIA | P15: 3 | Q15: disqualified | R15: 0 | S15: 1 | T15: 2026-08-11 s/CTA
A16: REVIEW | B16: nome_parcial | C16: 0.45 | D16: apos_comentario | E16: 1 | F16: 1 | G16: primeiro_ultimo | H16: Rafael Silva | I16: orafaelnsilva@gmail.com | J16: +5511972233392 | K16: 2026-08-25 14:04 | L16: Rafael Nunes da Silva | M16: https://www.linkedin.com/in/orafaelnunes | N16: Estratégia Digital, Inovação e Produtos SaaS | Foco em Crescimento, Dados e Experiência do Usuário | Q16: disqualified | R16: 30 | S16: 2 | T16: 2026-07-14 FLOW | 2026-08-11 s/CTA
A17: REVIEW | B17: nome_parcial | C17: 0.45 | D17: apos_comentario | E17: 1 | F17: 1 | G17: primeiro_ultimo | H17: Rafael Silva | I17: orafaelnsilva@gmail.com | J17: +5511972233392 | K17: 2026-08-25 14:04 | L17: Rafael Oliveira Silva | M17: https://www.linkedin.com/in/rafael-oliveira-silva-a7233b1a5 | N17: Supervisor de Inside Sales | O17: Sua LUZ | Q17: disqualified | R17: 30 | S17: 1 | T17: 2026-08-11 s/CTA
A18: REVIEW | B18: nome_parcial | C18: 0.45 | D18: apos_comentario | E18: 1 | F18: 1 | G18: primeiro_ultimo | H18: Rafael Silva | I18: orafaelnsilva@gmail.com | J18: +5511972233392 | K18: 2026-08-25 14:04 | L18: Rafael Gutierrez da Silva | M18: https://www.linkedin.com/in/rafael-gutierrez-da-silva-668a7279 | N18: Partner Manager | O18: Faiston | P18: 201 | Q18: qualified | R18: 70 | S18: 1 | T18: 2026-08-11 s/CTA
A20: Uma linha por par inscricao x lead candidato. Quando 'de' e maior que 1, a mesma inscricao do Tally casa com mais de um lead - e o caso do "Rafael Silva", com tres pessoas reais disputando a mesma inscricao. Regra do matcher: nome sozinho so decide com 3+ tokens e candidato unico; abaixo disso exige e-mail corporativo batendo com a empresa ou inscricao no formulario do post comentado.

Sheet Comentarios
A1: Nome no LinkedIn | B1: Match | C1: Cargo | D1: Empresa | E1: Comentou em | F1: Post de | G1: Autor do post | H1: CTA do post | I1: Gancho do post | J1: O que comentou
A2: André Soczek | B2: MATCHED | C2: Fundador | D2: Apartamentos Curitiba | E2: 2026-08-13 | F2: 2026-08-11 | G2: Victor Baggio | I2: Transformei a rotina de um SDR em 36 Skills para usar no Claude. | J2: SDR
A3: Celio Milo de Andrade | B3: REVIEW | C3: Coordenador de licitações | D3: Cantu Inc | E3: 2026-07-30 | F3: 2026-07-29 | G3: Victor Baggio | H3: OS | I3: Criei um "Segundo Cérebro" pra minha empresa com o Claude. Nunca fui tão produtivo na minha vida! | J3: OS
A4: Cíntia Fonseca | B4: REVIEW | C4: SDR / BDR | D4: Vkron Agência de Marketing Digital | E4: 2026-08-12 | F4: 2026-08-11 | G4: Victor Baggio | I4: Transformei a rotina de um SDR em 36 Skills para usar no Claude. | J4: sdr
A5: Eduardo Abreu | B5: REVIEW | C5: Executivo de contas | D5: Business Innovation Ltda | E5: 2026-08-12 | F5: 2026-08-11 | G5: Victor Baggio | I5: Transformei a rotina de um SDR em 36 Skills para usar no Claude. | J5: SDR
A6: Gabriel de Lima P. | B6: REVIEW | C6: Executivo de Vendas | Inside Sales | SDR | BDR | Hunter | B2B | Outbound | Analista TI | Analista de Suporte | Cloud | Projetos Infraestrutura | ADS | Programador | Tecnologia | SQL | D6: Senior Mega SPO | E6: 2026-08-11 | F6: 2026-08-11 | G6: Victor Baggio | I6: Transformei a rotina de um SDR em 36 Skills para usar no Claude. | J6: sdr
A7: Hudson Leonardo Oliveira | B7: REVIEW | C7: Sócio e Consultor de Negócios | D7: Consultólogo | E7: 2026-07-30 | F7: 2026-07-29 | G7: Victor Baggio | H7: OS | I7: Criei um "Segundo Cérebro" pra minha empresa com o Claude. Nunca fui tão produtivo na minha vida! | J7: OS
A8: Hudson Leonardo Oliveira | B8: REVIEW | C8: Sócio e Consultor de Negócios | D8: Consultólogo | E8: 2026-08-11 | F8: 2026-08-11 | G8: Victor Baggio | I8: Transformei a rotina de um SDR em 36 Skills para usar no Claude. | J8: SDR
A9: João Pedro Maya | B9: MATCHED | C9: Projetos | Reestruturação de processos | Operações | Trilingue | E9: 2026-08-12 | F9: 2026-08-11 | G9: Victor Baggio | I9: Transformei a rotina de um SDR em 36 Skills para usar no Claude. | J9: SDR
A10: Luan Garcia Hinkel | B10: MATCHED | C10: Sales Operations Junior | D10: HostGator América Latina | E10: 2026-07-29 | F10: 2026-07-29 | G10: Victor Baggio | H10: OS | I10: Criei um "Segundo Cérebro" pra minha empresa com o Claude. Nunca fui tão produtivo na minha vida! | J10: OS
A11: Luan Garcia Hinkel | B11: MATCHED | C11: Sales Operations Junior | D11: HostGator América Latina | E11: 2026-08-12 | F11: 2026-08-11 | G11: Victor Baggio | I11: Transformei a rotina de um SDR em 36 Skills para usar no Claude. | J11: SDR
A12: Marina Rachewsky Lemos | B12: REVIEW | C12: Embaixadora | Influenciadora | D12: HubSpot | E12: 2026-05-28 | F12: 2026-05-27 | H12: Sem CTA | I12: Fazer forecast de vendas sempre foi uma m*rda | J12: Fabyulla Corrêa
A13: Marina Rachewsky Lemos | B13: REVIEW | C13: Embaixadora | Influenciadora | D13: HubSpot | E13: 2026-07-29 | F13: 2026-07-29 | G13: Victor Baggio | H13: OS | I13: Criei um "Segundo Cérebro" pra minha empresa com o Claude. Nunca fui tão produtivo na minha vida! | J13: OS
A14: Nicolò Giusti de Marle | B14: REVIEW | C14: Co-Founder | D14: LUXIA | E14: 2026-08-21 | F14: 2026-08-11 | G14: Victor Baggio | I14: Transformei a rotina de um SDR em 36 Skills para usar no Claude. | J14: SDR
A15: Patricia Zaniratto | B15: REVIEW | C15: Especialista em Prospecção B2B | D15: Zaniratto Comercial | E15: 2026-08-12 | F15: 2026-08-11 | G15: Victor Baggio | I15: Transformei a rotina de um SDR em 36 Skills para usar no Claude. | J15: SDR
A16: Rafael Gutierrez da Silva | B16: REVIEW | C16: Partner Manager | D16: Faiston | E16: 2026-08-12 | F16: 2026-08-11 | G16: Victor Baggio | I16: Transformei a rotina de um SDR em 36 Skills para usar no Claude. | J16: SDR
A17: Rafael Nunes da Silva | B17: REVIEW | C17: Estratégia Digital, Inovação e Produtos SaaS | Foco em Crescimento, Dados e Experiência do Usuário | E17: 2026-07-14 | F17: 2026-07-14 | G17: Victor Baggio | H17: FLOW | I17: Enriquecimento de dados B2B no Brasil sempre foi complicado. | J17: Flow
A18: Rafael Nunes da Silva | B18: REVIEW | C18: Estratégia Digital, Inovação e Produtos SaaS | Foco em Crescimento, Dados e Experiência do Usuário | E18: 2026-08-11 | F18: 2026-08-11 | G18: Victor Baggio | I18: Transformei a rotina de um SDR em 36 Skills para usar no Claude. | J18: SDR
A19: Rafael Oliveira Silva | B19: REVIEW | C19: Supervisor de Inside Sales | D19: Sua LUZ | E19: 2026-08-12 | F19: 2026-08-11 | G19: Victor Baggio | I19: Transformei a rotina de um SDR em 36 Skills para usar no Claude. | J19: SDR
A20: Rodrigo Nascimento | B20: REVIEW | C20: Head Comercial | Head de Produto · SaaS · RevOps · Go-to-Market · Pré-vendas · IA aplicada a Vendas | D20: Keeta | E20: 2026-07-29 | F20: 2026-07-29 | G20: Victor Baggio | H20: OS | I20: Criei um "Segundo Cérebro" pra minha empresa com o Claude. Nunca fui tão produtivo na minha vida! | J20: OS
A21: Rodrigo Nascimento | B21: REVIEW | C21: Head Comercial | Head de Produto · SaaS · RevOps · Go-to-Market · Pré-vendas · IA aplicada a Vendas | D21: Keeta | E21: 2026-08-12 | F21: 2026-08-11 | G21: Victor Baggio | I21: Transformei a rotina de um SDR em 36 Skills para usar no Claude. | J21: SDR
A22: Sidnei Brianti | B22: REVIEW | C22: Fundador | D22: LinkaTudo | E22: 2026-08-11 | F22: 2026-08-11 | G22: Victor Baggio | I22: Transformei a rotina de um SDR em 36 Skills para usar no Claude. | J22: SDR
A23: Vinícius Silva | B23: REVIEW | C23: Consultor & Estrategista Digital | D23: Aigle Aeternus Hub | E23: 2026-07-03 | F23: 2026-07-03 | G23: Victor Baggio | H23: FABLE | I23: Você só tem mais 5 dias pra usar o Claude Fable sem pagar extra. | J23: Fable
A24: Vinícius Silva | B24: REVIEW | C24: Consultor & Estrategista Digital | D24: Aigle Aeternus Hub | E24: 2026-07-14 | F24: 2026-07-14 | G24: Victor Baggio | H24: FLOW | I24: Enriquecimento de dados B2B no Brasil sempre foi complicado. | J24: FLOW
A25: Vinícius Silva | B25: REVIEW | C25: Consultor & Estrategista Digital | D25: Aigle Aeternus Hub | E25: 2026-07-29 | F25: 2026-07-29 | G25: Victor Baggio | H25: OS | I25: Criei um "Segundo Cérebro" pra minha empresa com o Claude. Nunca fui tão produtivo na minha vida! | J25: OS
A26: Vinícius Silva | B26: REVIEW | C26: Consultor & Estrategista Digital | D26: Aigle Aeternus Hub | E26: 2026-08-11 | F26: 2026-08-11 | G26: Victor Baggio | I26: Transformei a rotina de um SDR em 36 Skills para usar no Claude. | J26: SDR

Sheet Historico Tally
A1: Nome (Tally) | B1: E-mail | C1: Ja era audiencia? | D1: Lead magnet baixado antes | E1: Form ID | F1: Baixado em | G1: Telefone naquele form
A2: Andrei Lucas | B2: andreidias.96@outlook.com | C2: Baixou outro lead magnet | D2: O Setup inicial do OS da sua empresa | E2: 7RO9QA | F2: 2026-07-30 21:20
A3: Celio Andrade | B3: cmilodeandrade@gmail.com | C3: Comentou em post | D3: Claude para Pequenos Negócios | E3: lb1gzV | F3: 2026-07-24 18:02
A4: Celio Andrade | B4: cmilodeandrade@gmail.com | C4: Comentou em post | D4: O Setup inicial do OS da sua empresa | E4: 7RO9QA | F4: 2026-07-30 13:22
A5: Cíntia Fonseca | B5: cintiafonseeca@gmail.com | C5: Comentou em post | D5: 36 Skills de SDR para Claude | E5: VLaVrE | F5: 2026-08-25 13:02 | G5: +5513996215600
A6: FELIPE NUNES | B6: felipearian10197@gmail.com | C6: Baixou outro lead magnet | D6: Claude Flabe 5 | E6: kdpqLe | F6: 2026-07-03 12:23
A7: FELIPE NUNES | B7: fereservas@gmail.com | C7: Baixou outro lead magnet | D7: Claude Flabe 5 | E7: kdpqLe | F7: 2026-07-03 13:41
A8: FELIPE NUNES | B8: fereservas@gmail.com | C8: Baixou outro lead magnet | D8: KipFlow - API brasileira boa de verdade | E8: EkEkX4 | F8: 2026-07-10 17:02
A9: FELIPE NUNES | B9: felipearian10197@gmail.com | C9: Baixou outro lead magnet | D9: KipFlow - API brasileira boa de verdade | E9: EkEkX4 | F9: 2026-07-14 03:47
A10: FELIPE NUNES | B10: fereservas@gmail.com | C10: Baixou outro lead magnet | D10: O Setup inicial do OS da sua empresa | E10: 7RO9QA | F10: 2026-07-29 03:36
A11: FELIPE NUNES | B11: fereservas@gmail.com | C11: Baixou outro lead magnet | D11: 36 Skills de SDR para Claude | E11: VLaVrE | F11: 2026-08-05 02:27
A12: FELIPE NUNES | B12: fereservas@gmail.com | C12: Baixou outro lead magnet | D12: 36 Skills de SDR para Claude | E12: VLaVrE | F12: 2026-08-05 12:12
A13: FELIPE NUNES | B13: fereservas@gmail.com | C13: Baixou outro lead magnet | D13: 36 Skills de SDR para Claude | E13: VLaVrE | F13: 2026-08-05 12:13
A14: FELIPE NUNES | B14: fereservas@gmail.com | C14: Baixou outro lead magnet | D14: 36 Skills de SDR para Claude | E14: VLaVrE | F14: 2026-08-11 14:27
A15: FELIPE NUNES | B15: fereservas@gmail.com | C15: Baixou outro lead magnet | D15: 36 Skills de SDR para Claude | E15: VLaVrE | F15: 2026-08-11 14:31
A16: FELIPE NUNES | B16: felipearian10197@gmail.com | C16: Baixou outro lead magnet | D16: 36 Skills de SDR para Claude | E16: VLaVrE | F16: 2026-08-14 13:23 | G16: +5511952960701
A17: FELIPE NUNES | B17: fereservas@gmail.com | C17: Baixou outro lead magnet | D17: KipFlow - API brasileira boa de verdade | E17: EkEkX4 | F17: 2026-08-14 19:52 | G17: +5511952960701
A18: FELIPE NUNES | B18: fereservas@gmail.com | C18: Baixou outro lead magnet | D18: Claude Flabe 5 | E18: kdpqLe | F18: 2026-08-17 20:37 | G18: +5511952960701
A19: Gustavo Santos | B19: gustavomaedoyt@gmail.com | C19: Baixou outro lead magnet | D19: O Setup inicial do OS da sua empresa | E19: 7RO9QA | F19: 2026-08-09 12:58
A20: marina lemos | B20: marinarlemos08@gmail.com | C20: Comentou em post | D20: Acesse o grupo VIP da Comunidade Playbook Lab | E20: EkG6vN | F20: 2026-08-25 19:04 | G20: +5548988191425
A21: Rafael Comin | B21: clientes.rafaelcomin@gmail.com | C21: Baixou outro lead magnet | D21: Claude Cowork para Vendas | E21: Y5q1gB | F21: 2026-08-11 12:41
A22: Rafael Silva | B22: orafaelnsilva@gmail.com | C22: Comentou em post | D22: 36 Skills de SDR para Claude | E22: VLaVrE | F22: 2026-08-11 17:50
A23: Rafael Silva | B23: orafaelnsilva@gmail.com | C23: Comentou em post | D23: 36 Skills de SDR para Claude | E23: VLaVrE | F23: 2026-08-11 17:51
A24: Rafael Silva | B24: orafaelnsilva@gmail.com | C24: Comentou em post | D24: 36 Skills de SDR para Claude | E24: VLaVrE | F24: 2026-08-26 12:16 | G24: +5511972233392
A25: Sidnei Brianti | B25: scbrianti2022@gmail.com | C25: Comentou em post | D25: 36 Skills de SDR para Claude | E25: VLaVrE | F25: 2026-08-11 22:36
A26: Sidnei Brianti | B26: scbrianti2022@gmail.com | C26: Comentou em post | D26: 36 Skills de SDR para Claude | E26: VLaVrE | F26: 2026-08-11 22:37
A27: Sidnei Brianti | B27: scbrianti2022@gmail.com | C27: Comentou em post | D27: 36 Skills de SDR para Claude | E27: VLaVrE | F27: 2026-08-11 23:39
A28: Teste Teste | B28: teste@teste.com.br | C28: Baixou outro lead magnet | D28: KipFlow - API brasileira boa de verdade | E28: EkEkX4 | F28: 2026-07-14 14:15
A29: Teste Teste | B29: teste@teste.com.br | C29: Baixou outro lead magnet | D29: 18 MCPs + o guia de instalação completo | E29: jaqkJJ | F29: 2026-07-28 16:29
A30: Teste Teste | B30: teste@teste.com.br | C30: Baixou outro lead magnet | D30: 36 Skills de SDR para Claude | E30: VLaVrE | F30: 2026-08-19 13:20 | G30: +5599999999999

Sheet ICP
A1: Perfil de quem se inscreveu E ja tinha comentado em post nosso
A2: Contagens calculadas por formula sobre a aba Inscritos, sempre restritas a Classificacao = Real.
A4: Corte | B4: Pessoas | C4: Leitura
A5: Area classificada como vendas | B5: =COUNTIFS(Inscritos!$A$2:$A$56,"Real",Inscritos!$B$2:$B$56,"Comentou em post",Inscritos!$U$2:$U$56,"vendas") | C5: Classificacao automatica; o titulo real mostra mais - ver coluna Cargo / headline.
A6: Senioridade c-level | B6: =COUNTIFS(Inscritos!$A$2:$A$56,"Real",Inscritos!$B$2:$B$56,"Comentou em post",Inscritos!$T$2:$T$56,"c-level") | C6: Fundadores de operacao enxuta.
A7: Senioridade diretoria ou gerencia | B7: =COUNTIFS(Inscritos!$A$2:$A$56,"Real",Inscritos!$B$2:$B$56,"Comentou em post",Inscritos!$T$2:$T$56,"diretoria")+COUNTIFS(Inscritos!$A$2:$A$56,"Real",Inscritos!$B$2:$B$56,"Comentou em post",Inscritos!$T$2:$T$56,"gerencia") | C7: Camada que decide processo comercial.
A8: Senioridade operacional ou coordenacao | B8: =COUNTIFS(Inscritos!$A$2:$A$56,"Real",Inscritos!$B$2:$B$56,"Comentou em post",Inscritos!$T$2:$T$56,"operacional")+COUNTIFS(Inscritos!$A$2:$A$56,"Real",Inscritos!$B$2:$B$56,"Comentou em post",Inscritos!$T$2:$T$56,"coordenacao") | C8: Quem executa a rotina que o post prometia automatizar.
A9: Senioridade nao identificada | B9: =COUNTIFS(Inscritos!$A$2:$A$56,"Real",Inscritos!$B$2:$B$56,"Comentou em post",Inscritos!$T$2:$T$56,"desconhecido") | C9: Perfil sem cargo estruturado no scrape - da para ler pelo headline.
A10: Empresa com mais de 1.000 funcionarios | B10: =COUNTIFS(Inscritos!$A$2:$A$56,"Real",Inscritos!$B$2:$B$56,"Comentou em post",Inscritos!$W$2:$W$56,">1000") | C10: HubSpot, Keeta e Cantu - a excecao, nao a regra.
A11: Empresa entre 11 e 1.000 | B11: =COUNTIFS(Inscritos!$A$2:$A$56,"Real",Inscritos!$B$2:$B$56,"Comentou em post",Inscritos!$W$2:$W$56,">=11")-COUNTIFS(Inscritos!$A$2:$A$56,"Real",Inscritos!$B$2:$B$56,"Comentou em post",Inscritos!$W$2:$W$56,">1000") | C11: HostGator (316), Vkron (27), Senior Mega SPO (11). Faiston (201) aparece como candidato alternativo da colisao "Rafael Silva" - conta na aba Matches, nao aqui.
A12: Empresa com 10 ou menos | B12: =COUNTIFS(Inscritos!$A$2:$A$56,"Real",Inscritos!$B$2:$B$56,"Comentou em post",Inscritos!$W$2:$W$56,">0")-COUNTIFS(Inscritos!$A$2:$A$56,"Real",Inscritos!$B$2:$B$56,"Comentou em post",Inscritos!$W$2:$W$56,">10") | C12: Consultores e fundadores solo.
A13: Sem empresa identificada | B13: =COUNTIFS(Inscritos!$A$2:$A$56,"Real",Inscritos!$B$2:$B$56,"Comentou em post")-COUNTIFS(Inscritos!$A$2:$A$56,"Real",Inscritos!$B$2:$B$56,"Comentou em post",Inscritos!$W$2:$W$56,">0") | C13: Perfil sem vinculo atual no scrape.
A14: Qualified pelo score atual | B14: =COUNTIFS(Inscritos!$A$2:$A$56,"Real",Inscritos!$B$2:$B$56,"Comentou em post",Inscritos!$AB$2:$AB$56,"qualified") | C14: Marina Lemos (95) e Rodrigo Nascimento (55).
A15: Disqualified pelo score atual | B15: =COUNTIFS(Inscritos!$A$2:$A$56,"Real",Inscritos!$B$2:$B$56,"Comentou em post",Inscritos!$AB$2:$AB$56,"disqualified") | C15: Score entre 30 e 45 na maioria.
A16: Comentou em 2 ou mais posts | B16: =COUNTIFS(Inscritos!$A$2:$A$56,"Real",Inscritos!$B$2:$B$56,"Comentou em post",Inscritos!$AE$2:$AE$56,">=2") | C16: Recorrencia, nao acaso.
A17: Tambem baixou outro lead magnet | B17: =COUNTIFS(Inscritos!$A$2:$A$56,"Real",Inscritos!$B$2:$B$56,"Comentou em post",Inscritos!$AJ$2:$AJ$56,">0") | C17: Comentou E baixou material antes: o sinal mais forte de intencao que temos.
A19: A TENSAO QUE VALE DECIDIR
A20: Quase todo mundo que comentou, voltou e baixou material de novo esta marcado como disqualified, com score entre 30 e 45. Quem responde a esse tema e operador de vendas em empresa pequena ou media - SDR, inside sales, sales ops, consultor solo, fundador de time de 2 a 30 pessoas. E o mesmo publico do post de 11/08 sobre rotina de SDR, que voltou agora. Se esse perfil e ICP, o score precisa parar de puni-lo. Se nao e, a pauta que mais engaja e a que menos vende - e isso e decisao de conteudo, nao de dado.

Sheet Enriquecer
A1: Inscritos com e-mail corporativo e sem perfil de LinkedIn na base
A2: O dominio entrega a empresa. Caminho mais curto para nome novo com contexto.
A4: Nome | B4: E-mail | C4: Dominio | D4: Telefone | E4: Inscrito em | F4: Observacao
A5: Marina Medeiros | B5: marina.medeiros@aurum.com.br | C5: aurum.com.br | D5: +5548998021913 | E5: 2026-08-25 13:07
A6: Carolina Pereira | B6: carolina.botelho@braziljournal.com | C6: braziljournal.com | D6: +5511991375461 | E6: 2026-08-26 14:15
A7: Marina Costa | B7: marina@buscaepi.com | C7: buscaepi.com | D7: +5561982004620 | E7: 2026-08-25 13:11
A8: Mario Diqs | B8: mario@caju.com.br | C8: caju.com.br | D8: +5582999999999 | E8: 2026-08-25 21:43 | F8: Telefone aparenta ser falso.
A9: Ricardo Rosa | B9: ricardo@devotum.com.br | C9: devotum.com.br | D9: +5547992602655 | E9: 2026-08-25 15:12
A10: Gage Batista | B10: bfagner@hotmail.con | C10: hotmail.con | D10: +5571992867755 | E10: 2026-08-25 15:59 | F10: Erro de digitacao de hotmail.com - classificado como corporativo por engano.
A11: Arielle Domanski | B11: arielle.domanski@madeiramadeira.com.br | C11: madeiramadeira.com.br | D11: +5541996682298 | E11: 2026-08-25 19:05
A12: Andre Sousa | B12: andre.sousa@nilg.ai | C12: nilg.ai | D12: +351938016732 | E12: 2026-08-26 07:48
A13: Matheus Mazza | B13: matheus.mazza@rabbot.co | C13: rabbot.co | D13: +5511965810818 | E13: 2026-08-26 09:40
A14: Eduardo Moura | B14: eduardo@savessaude.com.br | C14: savessaude.com.br | D14: +5511978253731 | E14: 2026-08-25 14:03
A15: Victor Dias | B15: kettle_pessimist235@simplelogin.com | C15: simplelogin.com | D15: +5591935009813 | E15: 2026-08-26 08:13 | F15: Servico de e-mail descartavel; nao identifica empresa.

Sheet Diagnostico
A1: Por que o post de 25/08 nao entrou na base
A2: Evidencia lida de public.collection_runs e de cron.job no Supabase, em 26/08/2026.
A4: Quando | B4: Coletor | C4: Resultado | D4: O que aconteceu
A5: 25/08 09:30 UTC | B5: collect-linkedin | C5: sucesso - 7 itens | D5: Rodou no horario e funcionou. O post de rotinas so subiu por volta de 12:00 UTC (a primeira inscricao no Tally e 12:04), ou seja, depois desta coleta.
A6: 25/08 14:00 UTC | B6: catch-up | C6: nao disparou | D6: O job de recuperacao so roda se NAO houve coleta bem-sucedida nas ultimas 12h. A de 09:30 tinha dado certo, entao ele corretamente pulou - e o post perdeu a segunda chance do dia.
A7: 26/08 09:00 UTC | B7: collect-youtube | C7: parcial - actor ABORTED | D7: Primeiro sinal do problema do dia.
A8: 26/08 09:30 UTC | B8: collect-linkedin | C8: FALHOU - 3 contas | D8: "By launching this job you will exceed your remaining usage of $0.001342. Consider upgrading to a paid plan". Credito da Apify esgotado. Era esta rodada que pegaria o post.
A9: 26/08 10:00 UTC | B9: collect-instagram | C9: FALHOU | D9: Mesmo erro de credito da Apify.
A10: 18/08 | B10: todos | C10: FALHOU - 172 execucoes | D10: "Monthly usage hard limit exceeded". Voltou a funcionar em 19/08, o que sugere que o ciclo de cobranca da Apify reseta dia 19. Se for isso, sem recarga nada e coletado ate ~19/09.
A11: Continuo | B11: prospect-enrich-drain | C11: 144 execucoes por dia | D11: Roda a cada 10 minutos enriquecendo leads para prospeccao, na MESMA conta Apify. E o maior consumidor: o enriquecimento de prospeccao come o orcamento da coleta de conteudo.
A13: O QUE ISSO CUSTA NO CRUZAMENTO
A14: Sem o post em content_posts nao existe linha em post_lead_magnets ligando o post ao formulario xX8rVJ - e esse vinculo e a evidencia mais forte do matcher (confianca 0,96). E por isso que 12 nomes ficaram em REVIEW em vez de confirmados. Dois pontos a mais: o CTA ROTINAS nao existe no mapa CTA_TO_TALLY_FORM (leadMagnets.ts), e o post nao pediu comentario, entao provavelmente vai entrar sem cta_keyword - o vinculo tera de ser inserido a mao em post_lead_magnets, que e a fonte da verdade em producao.
A16: PARA DESTRAVAR
A17: 1. Recarregar a Apify ou esperar o reset do ciclo - e decisao de custo, nao tem jeito tecnico. 2. Enquanto isso, a prospeccao deste post nao depende da coleta: as inscricoes do Tally ja trazem nome, e-mail e telefone (aba Inscritos). 3. Quando o post entrar, inserir o vinculo em post_lead_magnets e rodar de novo o cruzamento - boa parte dos REVIEW deve virar confirmado sozinha. 4. Vale separar o orcamento de prospeccao do de conteudo, ou o enriquecimento vai continuar derrubando a coleta todo mes. 5. Vale rodar o coletor de LinkedIn duas vezes ao dia: com uma rodada as 09:30 UTC, um post publicado ao meio-dia espera 21h para ser capturado.
